docling_core/__init__.py
docling_core/cli/__init__.py
docling_core/cli/view.py
docling_core/py.typed
docling_core/resources/schemas/doc/ANN.json
docling_core/resources/schemas/doc/DOC.json
docling_core/resources/schemas/doc/OCR-output.json
docling_core/resources/schemas/doc/RAW.json
docling_core/resources/schemas/generated/ccs_document_schema.json
docling_core/resources/schemas/generated/minimal_document_schema_flat.json
docling_core/resources/schemas/search/search_doc_mapping.json
docling_core/resources/schemas/search/search_doc_mapping_v2.json
docling_core/search/__init__.py
docling_core/search/json_schema_to_search_mapper.py
docling_core/search/mapping.py
docling_core/search/meta.py
docling_core/search/package.py
docling_core/transforms/__init__.py
docling_core/transforms/chunker/__init__.py
docling_core/transforms/chunker/base.py
docling_core/transforms/chunker/hierarchical_chunker.py
docling_core/transforms/chunker/hybrid_chunker.py
docling_core/types/__init__.py
docling_core/types/base.py
docling_core/types/doc/__init__.py
docling_core/types/doc/base.py
docling_core/types/doc/document.py
docling_core/types/doc/labels.py
docling_core/types/doc/tokens.py
docling_core/types/doc/utils.py
docling_core/types/gen/__init__.py
docling_core/types/gen/generic.py
docling_core/types/io/__init__.py
docling_core/types/legacy_doc/__init__.py
docling_core/types/legacy_doc/base.py
docling_core/types/legacy_doc/doc_ann.py
docling_core/types/legacy_doc/doc_ocr.py
docling_core/types/legacy_doc/doc_raw.py
docling_core/types/legacy_doc/document.py
docling_core/types/legacy_doc/tokens.py
docling_core/types/nlp/__init__.py
docling_core/types/nlp/qa.py
docling_core/types/nlp/qa_labels.py
docling_core/types/rec/__init__.py
docling_core/types/rec/attribute.py
docling_core/types/rec/base.py
docling_core/types/rec/predicate.py
docling_core/types/rec/record.py
docling_core/types/rec/statement.py
docling_core/types/rec/subject.py
docling_core/utils/__init__.py
docling_core/utils/alias.py
docling_core-3.0.0.dist-info/LICENSE
docling_core-3.0.0.dist-info/METADATA
docling_core-3.0.0.dist-info/WHEEL
docling_core-3.0.0.dist-info/entry_points.txt
docling_core-3.0.0.dist-info/RECORD
