Metadata-Version: 2.1
Name: docling-core
Version: 3.0.0
Summary: A python library to define and validate data types in Docling.
Home-page: https://ds4sd.github.io/
License: MIT
Keywords: docling,discovery,etl,information retrieval,analytics,database,database schema,schema,JSON
Author: Cesar Berrospi Ramis
Author-email: ceb@zurich.ibm.com
Maintainer: Cesar Berrospi Ramis
Maintainer-email: ceb@zurich.ibm.com
Requires-Python: >=3.9,<4.0
Classifier: Development Status :: 5 - Production/Stable
Classifier: Intended Audience :: Developers
Classifier: Intended Audience :: Science/Research
Classifier: License :: OSI Approved :: MIT License
Classifier: Natural Language :: English
Classifier: Operating System :: OS Independent
Classifier: Programming Language :: Python :: 3
Classifier: Programming Language :: Python :: 3.9
Classifier: Programming Language :: Python :: 3.10
Classifier: Programming Language :: Python :: 3.11
Classifier: Programming Language :: Python :: 3.12
Classifier: Topic :: Database
Classifier: Topic :: Scientific/Engineering :: Information Analysis
Classifier: Topic :: Software Development :: Libraries :: Python Modules
Classifier: Typing :: Typed
Provides-Extra: chunking
Requires-Dist: jsonref (>=1.1.0,<2.0.0)
Requires-Dist: jsonschema (>=4.16.0,<5.0.0)
Requires-Dist: pandas (>=2.1.4,<3.0.0)
Requires-Dist: pillow (>=10.3.0,<11.0.0)
Requires-Dist: pydantic (>=2.6.0,<3.0.0,!=2.10.0,!=2.10.1,!=2.10.2)
Requires-Dist: pyyaml (>=5.1,<7.0.0)
Requires-Dist: semchunk (>=2.2.0,<3.0.0) ; extra == "chunking"
Requires-Dist: tabulate (>=0.9.0,<0.10.0)
Requires-Dist: transformers (>=4.34.0,<5.0.0) ; extra == "chunking"
Requires-Dist: typer (>=0.12.5,<0.13.0)
Requires-Dist: typing-extensions (>=4.12.2,<5.0.0)
Project-URL: Repository, https://github.com/DS4SD/docling-core
